magnumapi/__init__.py
magnumapi/geometry/Geometry.py
magnumapi/geometry/GeometryBuilder.py
magnumapi/geometry/GeometryCheck.py
magnumapi/geometry/GeometryFactory.py
magnumapi/geometry/GeometryPlot.py
magnumapi/geometry/SlottedGeometry.py
magnumapi/geometry/__init__.py
magnumapi/geometry/blocks/Block.py
magnumapi/geometry/blocks/CosThetaBlock.py
magnumapi/geometry/blocks/RectangularBlock.py
magnumapi/geometry/blocks/__init__.py
magnumapi/geometry/definitions/AbsoluteCosThetaBlockDefinition.py
magnumapi/geometry/definitions/BlockDefinition.py
magnumapi/geometry/definitions/CosThetaBlockDefinition.py
magnumapi/geometry/definitions/HomogenizedBlockDefinition.py
magnumapi/geometry/definitions/HomogenizedRectangularBlockDefinition.py
magnumapi/geometry/definitions/LayerDefinition.py
magnumapi/geometry/definitions/RectangularBlockDefinition.py
magnumapi/geometry/definitions/RelativeCosThetaBlockDefinition.py
magnumapi/geometry/definitions/__init__.py
magnumapi/geometry/geometry_symmetries.py
magnumapi/geometry/primitives/Arc.py
magnumapi/geometry/primitives/Area.py
magnumapi/geometry/primitives/Line.py
magnumapi/geometry/primitives/Point.py
magnumapi/geometry/primitives/__init__.py
magnum_api-0.7.2.dist-info/LICENSE
magnum_api-0.7.2.dist-info/WHEEL
magnum_api-0.7.2.dist-info/METADATA
magnum_api-0.7.2.dist-info/RECORD
