Metadata-Version: 2.1
Name: magnum-api
Version: 0.7.2
Summary: 
Home-page: https://gitlab.cern.ch/chart-magnum/magnum-api
License: MIT
Author: mmaciejewski
Author-email: michal.maciejewski@ief.ee.ethz.ch
Requires-Python: >=3.9,<3.12
Classifier: Intended Audience :: Education
Classifier: License :: OSI Approved :: MIT License
Classifier: Operating System :: OS Independent
Classifier: Programming Language :: Python :: 3
Classifier: Programming Language :: Python :: 3.9
Classifier: Programming Language :: Python :: 3.10
Classifier: Programming Language :: Python :: 3.11
Classifier: Programming Language :: Python :: 3
Requires-Dist: Shapely (>=1.8.2,<2.0.0)
Requires-Dist: ipyaggrid (>=0.2.2,<0.3.0)
Requires-Dist: matplotlib (>=3.5.2,<4.0.0)
Requires-Dist: numpy (>=1.23.1,<2.0.0)
Requires-Dist: pandas (>=1.4.3,<2.0.0)
Requires-Dist: pydantic (>=1.9.1,<2.0.0)
Requires-Dist: pymbse-commons (>=0.0.6,<0.0.7)
Requires-Dist: roxie-api (>=0.0.15,<0.0.16)
Project-URL: Repository, https://gitlab.cern.ch/chart-magnum/magnum-api
